genosolver/__init__.py
genosolver/_version.py
genosolver/genosolver.py
genosolver-0.1.0.6.dist-info/LICENSE
genosolver-0.1.0.6.dist-info/METADATA
genosolver-0.1.0.6.dist-info/WHEEL
genosolver-0.1.0.6.dist-info/top_level.txt
genosolver-0.1.0.6.dist-info/RECORD
