Metadata-Version: 2.1
Name: genosolver
Version: 0.1.0.6
Summary: GENO is a solver for non-linear optimization problems. It can solve constrained and unconstrained problems.
Home-page: http://www.geno-project.org
Author: Soeren Laue
Author-email: soeren.laue@uni-jena.de
License: AGPL-3.0
Project-URL: Source, https://github.com/slaue/genosolver/
Keywords: optimization,machine_learning
Platform: UNKNOWN
Classifier: Intended Audience :: Developers
Classifier: Intended Audience :: Science/Research
Classifier: Topic :: Scientific/Engineering
Classifier: Topic :: Software Development
Classifier: License :: OSI Approved :: GNU Affero General Public License v3
Classifier: Operating System :: MacOS :: MacOS X
Classifier: Operating System :: Microsoft :: Windows
Classifier: Operating System :: POSIX :: Linux
Classifier: Programming Language :: Python :: 3.6
Classifier: Programming Language :: Python :: 3.7
Classifier: Programming Language :: Python :: 3.8
Classifier: Programming Language :: Python :: 3.9
Requires-Python: >=3.6
Requires-Dist: numpy (>=1.17)
Requires-Dist: packaging
